asyncpow/__init__.py
asyncpow/apis/media.py
asyncpow/apis/movie.py
asyncpow/apis/request.py
asyncpow/apis/search.py
asyncpow/apis/status.py
asyncpow/apis/tv.py
asyncpow/apis/user.py
asyncpow/const.py
asyncpow/exceptions.py
asyncpow/models/common.py
asyncpow/models/issue.py
asyncpow/models/media.py
asyncpow/models/movie.py
asyncpow/models/request.py
asyncpow/models/search.py
asyncpow/models/status.py
asyncpow/models/tv.py
asyncpow/models/user.py
asyncpow/overseerr.py
asyncpow/py.typed
asyncpow/utils/api_key.py
asyncpow/utils/http.py
asyncpow-0.5.0.dist-info/METADATA
asyncpow-0.5.0.dist-info/WHEEL
asyncpow-0.5.0.dist-info/RECORD
