Metadata-Version: 2.1
Name: asyncpow
Version: 0.5.0
Summary: Asynchronous Python Overseerr Wrapper
Home-page: https://github.com/totaldebug/asyncpow
License: MIT
Keywords: wled,api,async,client
Author: Steven Marks - TotalDebug
Maintainer: Steven Marks - TotalDebug
Requires-Python: >=3.12,<4.0
Classifier: Development Status :: 4 - Beta
Classifier: Framework :: AsyncIO
Classifier: Intended Audience :: Developers
Classifier: License :: OSI Approved :: MIT License
Classifier: Natural Language :: English
Classifier: Programming Language :: Python :: 3
Classifier: Programming Language :: Python :: 3.12
Classifier: Topic :: Software Development :: Libraries :: Python Modules
Requires-Dist: aiohttp (>=3.9.3,<4.0.0)
Requires-Dist: backoff (>=2.2.1,<3.0.0)
Requires-Dist: cachetools (>=5.3.3,<6.0.0)
Requires-Dist: yarl (>=1.9.4,<2.0.0)
Project-URL: Repository, https://github.com/totaldebug/asyncpow
